Metadata-Version: 2.1
Name: RapidEDA
Version: 0.1
Summary: Rapid Automated Exploratory Data Analysis for any dataset.
Home-page: https://github.com/devashrichaudhari/RapidEDA.git
Author: Devashri Chaudhari
Author-email: devashrichaudhari@gmail.com
License: MIT
Download-URL: https://github.com/devashrichaudhari/RapidEDA/archive/refs/tags/v.01.tar.gz
Keywords: EDA,AutoEDA,automated eda
Platform: UNKNOWN
Classifier: Development Status :: 3 - Alpha
Classifier: Intended Audience :: Developers
Classifier: Topic :: Software Development :: Build Tools
Classifier: License :: OSI Approved :: MIT License
Classifier: Programming Language :: Python :: 3
Classifier: Programming Language :: Python :: 3.9
Classifier: Programming Language :: Python :: 3.8
Classifier: Programming Language :: Python :: 3.7
License-File: LICENSE.txt
